git_digest/__init__.py
git_digest/__main__.py
git_digest/cli.py
git_digest/const.py
git_digest/types.py
git_digest/utils/git.py
git_digest/utils/llm.py
git_digest-0.7.3.dist-info/WHEEL
git_digest-0.7.3.dist-info/entry_points.txt
git_digest-0.7.3.dist-info/METADATA
git_digest-0.7.3.dist-info/RECORD
