Metadata-Version: 2.3
Name: git-digest
Version: 0.7.3
Summary: Summarize recent Git contributions into clear, human-readable updates using AI
Keywords: git,commit,summary,ai,llm,report,changelog,development,productivity
Author: Rafid K.
Author-email: Rafid K. <rafidka@gmail.com>
License: MIT License
Classifier: Development Status :: 4 - Beta
Classifier: Environment :: Console
Classifier: Intended Audience :: Developers
Classifier: License :: OSI Approved :: MIT License
Classifier: Operating System :: OS Independent
Classifier: Programming Language :: Python :: 3
Classifier: Programming Language :: Python :: 3.12
Classifier: Programming Language :: Python :: 3.13
Classifier: Topic :: Software Development :: Version Control :: Git
Classifier: Topic :: Software Development :: Libraries :: Python Modules
Classifier: Topic :: Utilities
Classifier: Typing :: Typed
Requires-Dist: gitpython>=3.1.45
Requires-Dist: typer>=0.16.1
Requires-Dist: openai>=1.100.0
Maintainer: Rafid K.
Maintainer-email: Rafid K. <rafidka@gmail.com>
Requires-Python: >=3.12
Project-URL: Changelog, https://github.com/rafidka/git-digest/releases
Project-URL: Documentation, https://github.com/rafidka/git-digest#readme
Project-URL: Homepage, https://github.com/rafidka/git-digest
Project-URL: Issues, https://github.com/rafidka/git-digest/issues
Project-URL: Repository, https://github.com/rafidka/git-digest
